mlit/__init__.py
mlit/__main__.py
mlit/models/__init__.py
mlit/models/common.py
mlit/models/t5/__init__.py
mlit/models/t5/helpers/__init__.py
mlit/models/t5/helpers/decoder.py
mlit/models/t5/helpers/encoder.py
mlit/models/t5/helpers/loader.py
mlit/models/t5/helpers/model.py
mlit/onnx_support/__init__.py
mlit/onnx_support/export.py
mlit/onnx_support/load.py
mlit/onnx_support/quantize.py
mlit-0.1.6.dist-info/METADATA
mlit-0.1.6.dist-info/WHEEL
mlit-0.1.6.dist-info/top_level.txt
mlit-0.1.6.dist-info/RECORD
