Metadata-Version: 2.1
Name: mlit
Version: 0.1.6
Summary: ML inference tools
Home-page: UNKNOWN
Author: roman@kalyakin.com
License: UNKNOWN
Keywords: ML,hugginface,onnx
Platform: Linux
Platform: Mac OS X
Platform: Windows
Classifier: License :: OSI Approved :: MIT License
Classifier: Programming Language :: Python
Classifier: Programming Language :: Python :: 3
Classifier: Programming Language :: Python :: 3.7
Requires-Python: >=3.7
Requires-Dist: transformers[torch] (>=4.4.0.dev0)
Requires-Dist: onnxruntime (>=1.7.0)
